{
    "name":"UPC",
    "faculties":[
        {
            "faculty":"EETAC",
            "degrees":[
                {
                    "name":"Ingeniería de Sistemas Aeroespaciales (menciones en Aeronavegación/Aeropuertos)",
                    "subjects":[
                        {
                            "name":"Fisica"
                        },
                        {
                            "name":"Quimica"
                        },
                        {
                            "name":"Infraestructures del Transport Aeri"
                        },
                        {
                            "name":"Termodinámica"
                        },
                        {
                            "name":"Aerodinámica"
                        },
                        {
                            "name":"Expresión Gráfica"
                        },
                        {
                            "name":"Estructures i Resistència dels Materials"
                        },
                        {
                            "name":"Mecànica de Vol"
                        }
                    ]
                },
                {
                    "name":"Ingeniería de Sistemas de Telecomunicación",
                    "subjects":[
                        {
                            "name":"Fisica"
                        },
                        {
                            "name":"Interconnexió de Xarxes"
                        },
                        {
                            "name":"Enginyeria de Software Ràdio"
                        },
                        {
                            "name":"Disseny de Serveis i Aplicacions"
                        },
                        {
                            "name":"Comunicacions Sense Fils"
                        }
                    ]
                },
                {
                    "name":"Ingeniería Telemática",
                    "subjects":[
                        {
                            "name":"Anàlisi i Dimensionament de Xarxes"
                        },
                        {
                            "name":"Infraestructures i Operació de Telecomunicacions"
                        },
                        {
                            "name":"Tecnologies d'Informació Quàntica"
                        },
                        {
                            "name":"Disseny de Serveis i Aplicacions"
                        },
                        {
                            "name":"Enginyeria d'Aplicacions"
                        }
                    ]
                },
                {
                    "name":"Doble titulación de grado en Ingeniería Aeroespacial e Ingeniería de Sistemas de Telecomunicación",
                    "subjects":[
                        {
                            "name":"Fisica"
                        },
                        {
                            "name":"Interconnexió de Xarxes"
                        },
                        {
                            "name":"Enginyeria de Software Ràdio"
                        },
                        {
                            "name":"Disseny de Serveis i Aplicacions"
                        },
                        {
                            "name":"Comunicacions Sense Fils"
                        },
                        {
                            "name":"Quimica"
                        },
                        {
                            "name":"Infraestructures del Transport Aeri"
                        },
                        {
                            "name":"Termodinámica"
                        },
                        {
                            "name":"Aerodinámica"
                        },
                        {
                            "name":"Expresión Gráfica"
                        },
                        {
                            "name":"Estructures i Resistència dels Materials"
                        },
                        {
                            "name":"Mecànica de Vol"
                        }
                    ]
                },
                {
                    "name":"Doble titulación de grado en Ingeniería Aeroespacial e Ingeniería Telemática",
                    "subjects":[
                        {
                            "name":"Anàlisi i Dimensionament de Xarxes"
                        },
                        {
                            "name":"Infraestructures i Operació de Telecomunicacions"
                        },
                        {
                            "name":"Tecnologies d'Informació Quàntica"
                        },
                        {
                            "name":"Disseny de Serveis i Aplicacions"
                        },
                        {
                            "name":"Enginyeria d'Aplicacions"
                        },
                        {
                            "name":"Fisica"
                        },
                        {
                            "name":"Quimica"
                        },
                        {
                            "name":"Infraestructures del Transport Aeri"
                        },
                        {
                            "name":"Termodinámica"
                        },
                        {
                            "name":"Aerodinámica"
                        },
                        {
                            "name":"Expresión Gráfica"
                        },
                        {
                            "name":"Estructures i Resistència dels Materials"
                        },
                        {
                            "name":"Mecànica de Vol"
                        }
                    ]
                }
            ]
        },
        {
            "faculty":"ESAB",
            "degrees":[
                {
                    "name":"Ingeniería de Ciencias Agronómicas",
                    "subjects":[
                        {
                            "name":"Fisica"
                        },
                        {
                            "name":"Quimica"
                        },
                        {
                            "name":"Produccion Animal"
                        },
                        {
                            "name":"Sistemas de Cultivo"
                        },
                        {
                            "name":"Alimentación y Nutrición Animal"
                        }
                    ]
                },
                {
                    "name":"Paisajismo",
                    "subjects":[
                        {
                            "name":"Dibujo 1"
                        },
                        {
                            "name":"Ecología"
                        },
                        {
                            "name":"Urbanismo y Paisaje I"
                        },
                        {
                            "name":"Complementos Paisajísticos desde la Construcción"
                        },
                        {
                            "name":"Taller de Proyectos VI"
                        }
                    ]
                },
                {
                    "name":"Ingeniería Alimentaria",
                    "subjects":[
                        {
                            "name":"Fisica"
                        },
                        {
                            "name":"Industrias Extractivas y Fermentativas"
                        },
                        {
                            "name":"Construcciones y Cálculo de Estructuras"
                        },
                        {
                            "name":"Diseño de Industrias Alimentarias"
                        },
                        {
                            "name":"Industrias Cárnicas y Lácteas"
                        }
                    ]
                }
            ]
        },
        {
            "faculty":"ESEIAAT",
            "degrees":[
                {
                    "name":"Ingeniería en Tecnologías Industriales",
                    "subjects":[
                        {
                            "name":"Fisica"
                        },
                        {
                            "name":"Sistemas Eléctricos"
                        },
                        {
                            "name":"Ciencia y Tecnología de los Materiales"
                        },
                        {
                            "name":"Métodos Matemáticos III"
                        },
                        {
                            "name":"Economía y Gestión de Empresa"
                        }
                    ]
                },
                {
                    "name":"Ingeniería Eléctrica ",
                    "subjects":[
                        {
                            "name":"Quimica 1"
                        },
                        {
                            "name":"Fundamentos de Informática"
                        },
                        {
                            "name":"Mecánica de Fluidos"
                        },
                        {
                            "name":"Control y Automatización Industrial"
                        },
                        {
                            "name":"Ampliación de Circuitos"
                        }
                    ]
                },
                {
                    "name":"Ingeniería en Tecnologías Aeroespaciales",
                    "subjects":[
                        {
                            "name":"Fisica"
                        },
                        {
                            "name":"Espacio Aéreo, Navegación e Infraestructuras"
                        },
                        {
                            "name":"Vehículos Aeroespaciales"
                        },
                        {
                            "name":"Sistemas Propulsivos"
                        },
                        {
                            "name":"Control Automático"
                        }
                    ]
                },
                {
                    "name":"Ingeniería en Vehículos Aeroespaciales",
                    "subjects":[
                        {
                            "name":"Termodinámica"
                        },
                        {
                            "name":"Vehículos Aeroespaciales"
                        },
                        {
                            "name":"Aerodinámica"
                        },
                        {
                            "name":"Aerodinámica Experimental"
                        },
                        {
                            "name":"Expresión Gráfica"
                        }
                    ]
                }
            ]
        }
    ]
}