[{
  "_id": {
    "$oid": "454151543030303032303230"
  },
  "subject": [
    {
      "$oid": "45455441435355424a303039"
    }
  ],
  "start": "2020-09-23",
  "end": "2021-02-10",
  "projects": [],
  "professors": [],
  "students": []
},{
  "_id": {
    "$oid": "454151503030303032303230"
  },
  "subject": [
    {
      "$oid": "45455441435355424a303039"
    }
  ],
  "start": "2019-02-17",
  "end": "2020-07-10",
  "projects": [],
  "professors": [],
  "students": []
},{
  "_id": {
    "$oid": "544951515430303032303230"
  },
  "subject": [
    {
      "$oid": "45455441435355424a303038"
    }
  ],
  "start": "2020-09-23",
  "end": "2021-02-10",
  "projects": [],
  "professors": [],
  "students": []
},{
  "_id": {
    "$oid": "445341515430303032303230"
  },
  "subject": [
    {
      "$oid": "45455441435355424a303037"
    }
  ],
  "start": "2020-09-23",
  "end": "2021-02-10",
  "projects": [],
  "professors": [],
  "students": [
    {
      "$oid": "5fc3ddbcfed3af0524171911"
    }
  ]
},{
  "_id": {
    "$oid": "455351543030303032303230"
  },
  "subject": [
    {
      "$oid": "45455441435355424a303036"
    }
  ],
  "start": "2020-09-23",
  "end": "2021-02-10",
  "projects": [],
  "professors": [],
  "students": [
    {
      "$oid": "5fc3ddbcfed3af0524171911"
    }
  ]
},{
  "_id": {
    "$oid": "495851543030303032303230"
  },
  "subject": [
    {
      "$oid": "45455441435355424a303035"
    }
  ],
  "start": "2020-09-23",
  "end": "2021-02-10",
  "projects": [],
  "professors": [],
  "students": []
},{
  "_id": {
    "$oid": "4d5651543030303032303230"
  },
  "subject": [
    {
      "$oid": "45455441435355424a303034"
    }
  ],
  "start": "2020-09-23",
  "end": "2021-02-10",
  "projects": [],
  "professors": [],
  "students": []
},{
  "_id": {
    "$oid": "414551543030303032303230"
  },
  "subject": [
    {
      "$oid": "45455441435355424a303033"
    }
  ],
  "start": "2020-09-23",
  "end": "2021-02-10",
  "projects": [],
  "professors": [],
  "students": []
},{
  "_id": {
    "$oid": "515551543030303032303230"
  },
  "subject": [
    {
      "$oid": "45455441435355424a303032"
    }
  ],
  "start": "2020-09-23",
  "end": "2021-02-10",
  "projects": [],
  "professors": [],
  "students": [
    {
      "$oid": "5fc3ddbcfed3af0524171911"
    }
  ]
},{
  "_id": {
    "$oid": "464951543030303032303230"
  },
  "subject": [
    {
      "$oid": "45455441435355424a303031"
    }
  ],
  "start": "2020-09-23",
  "end": "2021-02-10",
  "projects": [],
  "professors": [],
  "students": [
    {
      "$oid": "5fbcd8854506b76778cf3949"
    }
  ]
},{
  "_id": {
    "$oid": "504151543030303032303230"
  },
  "subject": [
    {
      "$oid": "45534142305355424a303031"
    }
  ],
  "start": "2020-09-23",
  "end": "2021-02-10",
  "projects": [],
  "professors": [],
  "students": [
    {
      "$oid": "5fc3ddbcfed3af0524171911"
    },
    {
      "$oid": "5fbcd8854506b76778cf3949"
    }
  ]
},{
  "_id": {
    "$oid": "534351543030303032303230"
  },
  "subject": [
    {
      "$oid": "45534142305355424a303032"
    }
  ],
  "start": "2020-09-23",
  "end": "2021-02-10",
  "projects": [],
  "professors": [],
  "students": [
    {
      "$oid": "5fc3ddbcfed3af0524171911"
    }
  ]
},{
  "_id": {
    "$oid": "444942515430303032303230"
  },
  "subject": [
    {
      "$oid": "45534142305355424a303033"
    }
  ],
  "start": "2020-09-23",
  "end": "2021-02-10",
  "projects": [],
  "professors": [],
  "students": []
},{
  "_id": {
    "$oid": "45434f515430303032303230"
  },
  "subject": [
    {
      "$oid": "45534142305355424a303034"
    }
  ],
  "start": "2020-09-23",
  "end": "2021-02-10",
  "projects": [],
  "professors": [],
  "students": [
    {
      "$oid": "5fbcd8854506b76778cf3949"
    }
  ]
},{
  "_id": {
    "$oid": "494546515430303032303230"
  },
  "subject": [
    {
      "$oid": "45534142305355424a303035"
    }
  ],
  "start": "2020-09-23",
  "end": "2021-02-10",
  "projects": [],
  "professors": [],
  "students": [
    {
      "$oid": "5fbcd8854506b76778cf3949"
    }
  ]
},{
  "_id": {
    "$oid": "49434c515430303032303230"
  },
  "subject": [
    {
      "$oid": "45534142305355424a303036"
    }
  ],
  "start": "2020-09-23",
  "end": "2021-02-10",
  "projects": [],
  "professors": [],
  "students": []
},{
  "_id": {
    "$oid": "534551543030303032303230"
  },
  "subject": [
    {
      "$oid": "455345494141545355303031"
    }
  ],
  "start": "2020-09-23",
  "end": "2021-02-10",
  "projects": [],
  "professors": [],
  "students": []
},{
  "_id": {
    "$oid": "43544d515430303032303230"
  },
  "subject": [
    {
      "$oid": "455345494141545355303032"
    }
  ],
  "start": "2020-09-23",
  "end": "2021-02-10",
  "projects": [],
  "professors": [],
  "students": []
},{
  "_id": {
    "$oid": "45414e495154303032303230"
  },
  "subject": [
    {
      "$oid": "455345494141545355303033"
    }
  ],
  "start": "2020-09-23",
  "end": "2021-02-10",
  "projects": [],
  "professors": [],
  "students": [
    {
      "$oid": "5fc3ddbcfed3af0524171911"
    }
  ]
},{
  "_id": {
    "$oid": "564151543030303032303230"
  },
  "subject": [
    {
      "$oid": "455345494141545355303034"
    }
  ],
  "start": "2020-09-23",
  "end": "2021-02-10",
  "projects": [],
  "professors": [],
  "students": [
    {
      "$oid": "5fc3ddbcfed3af0524171911"
    },
    {
      "$oid": "5fbcd8854506b76778cf3949"
    }
  ]
},{
  "_id": {
    "$oid": "414558515430303032303230"
  },
  "subject": [
    {
      "$oid": "455345494141545355303035"
    }
  ],
  "start": "2020-09-23",
  "end": "2021-02-10",
  "projects": [],
  "professors": [],
  "students": [
    {
      "$oid": "5fc3ddbcfed3af0524171911"
    },
    {
      "$oid": "5fbcd8854506b76778cf3949"
    }
  ]
}]